src/__init__.py
src/create_table.py
table_out-0.0.2.dist-info/METADATA
table_out-0.0.2.dist-info/WHEEL
table_out-0.0.2.dist-info/top_level.txt
table_out-0.0.2.dist-info/RECORD
